colorpattern/__init__.py
colorpattern/__main__.py
colorpattern/colorpattern.py
colorpattern-1.4.7.dist-info/LICENSE
colorpattern-1.4.7.dist-info/METADATA
colorpattern-1.4.7.dist-info/WHEEL
colorpattern-1.4.7.dist-info/top_level.txt
colorpattern-1.4.7.dist-info/RECORD
