Metadata-Version: 2.1
Name: colorpattern
Version: 1.4.7
Summary: Effortless console text colorization based on user-defined patterns.
Home-page: https://github.com/croketillo/colorpattern
Author: croketillo
Author-email: croketillo@gmail.com
License: GNU GENERAL PUBLIC LICENSE
Keywords: color pattern console colorpattern
Platform: UNKNOWN
Classifier: Environment :: Console
Classifier: Intended Audience :: Developers
Classifier: Programming Language :: Python :: 3
Classifier: Programming Language :: Python :: 3.6
Classifier: Programming Language :: Python :: 3.7
Classifier: Programming Language :: Python :: 3.8
Classifier: Topic :: Terminals
Classifier: Topic :: Software Development :: Libraries :: Python Modules
Classifier: Topic :: Utilities
Classifier: Topic :: Terminals
License-File: LICENSE
Requires-Dist: colorama
